auto_download_file/installer.py
auto_download_file-0.1.dist-info/METADATA
auto_download_file-0.1.dist-info/WHEEL
auto_download_file-0.1.dist-info/entry_points.txt
auto_download_file-0.1.dist-info/top_level.txt
auto_download_file-0.1.dist-info/RECORD
